Metadata-Version: 2.2
Name: awesome-citations
Version: 0.2.0
Summary: A comprehensive BibTeX bibliography management toolkit for academic research
Author: neardws
License: GPL-3.0-or-later
Project-URL: Homepage, https://github.com/neardws/Awesome-Citations
Project-URL: Repository, https://github.com/neardws/Awesome-Citations
Project-URL: Issues, https://github.com/neardws/Awesome-Citations/issues
Keywords: bibtex,bibliography,citations,academic,research,latex,ieee,acm,arxiv,crossref
Classifier: Development Status :: 4 - Beta
Classifier: Environment :: Console
Classifier: Intended Audience :: Science/Research
Classifier: Operating System :: OS Independent
Classifier: Programming Language :: Python :: 3
Classifier: Programming Language :: Python :: 3.8
Classifier: Programming Language :: Python :: 3.9
Classifier: Programming Language :: Python :: 3.10
Classifier: Programming Language :: Python :: 3.11
Classifier: Programming Language :: Python :: 3.12
Classifier: Topic :: Scientific/Engineering
Classifier: Topic :: Text Processing :: Markup :: LaTeX
Requires-Python: >=3.8
License-File: LICENSE
Requires-Dist: bibtexparser>=1.2.0
Requires-Dist: requests>=2.28.0
Requires-Dist: beautifulsoup4>=4.11.0
Requires-Dist: lxml>=4.9.0
Requires-Dist: tabulate>=0.9.0
Requires-Dist: pyyaml>=6.0
Requires-Dist: habanero>=1.2.0
Requires-Dist: scholarly>=1.7.0
Provides-Extra: selenium
Requires-Dist: selenium>=4.15.0; extra == "selenium"
Requires-Dist: webdriver-manager>=4.0.0; extra == "selenium"
Provides-Extra: dev
Requires-Dist: pytest>=7.4.0; extra == "dev"
Requires-Dist: pytest-cov>=4.1.0; extra == "dev"
Requires-Dist: pytest-timeout>=2.1.0; extra == "dev"
Requires-Dist: pytest-mock>=3.11.0; extra == "dev"
Provides-Extra: all
Requires-Dist: awesome-citations[dev,selenium]; extra == "all"
